tqsdk_ctpse/__init__.py
tqsdk_ctpse-1.0.1.dist-info/METADATA
tqsdk_ctpse-1.0.1.dist-info/WHEEL
tqsdk_ctpse-1.0.1.dist-info/top_level.txt
tqsdk_ctpse-1.0.1.dist-info/RECORD
