Metadata-Version: 2.1
Name: tqsdk-ctpse
Version: 1.0.1
Summary: TianQin SDK - ctpse lib
Home-page: https://www.shinnytech.com/tqsdk
Author: TianQin
Author-email: tianqincn@gmail.com
License: UNKNOWN
Platform: UNKNOWN
Requires-Python: >=3
